PdfBluePrint/0-temp_del.py
PdfBluePrint/1-pdf2img.py
PdfBluePrint/2-black2final.py
PdfBluePrint/3-img2pdf.py
PdfBluePrint/4-dir_del.py
PdfBluePrint/PdfBluePrint.py
PdfBluePrint/__init__.py
PdfBluePrint-0.0.4.dist-info/LICENSE
PdfBluePrint-0.0.4.dist-info/METADATA
PdfBluePrint-0.0.4.dist-info/WHEEL
PdfBluePrint-0.0.4.dist-info/entry_points.txt
PdfBluePrint-0.0.4.dist-info/top_level.txt
PdfBluePrint-0.0.4.dist-info/RECORD
