Metadata-Version: 2.1
Name: PdfBluePrint
Version: 0.0.4
Summary: Beautify PDF Colors for CMYK printer without K color
Home-page: https://github.com/jomoly/PdfBluePrint
Author: John Lu
Author-email: jomoly@gmail.com
License: LGPL
License-File: LICENSE
Requires-Dist: PyMuPDF
Requires-Dist: Pillow
Requires-Dist: numpy
Requires-Dist: img2pdf
